README.md
setup.py
param_persist/__init__.py
param_persist.egg-info/PKG-INFO
param_persist.egg-info/SOURCES.txt
param_persist.egg-info/dependency_links.txt
param_persist.egg-info/not-zip-safe
param_persist.egg-info/requires.txt
param_persist.egg-info/top_level.txt
param_persist/agents/__init__.py
param_persist/agents/base.py
param_persist/agents/sqlalchemy_agent.py
param_persist/sqlalchemy/__init__.py
param_persist/sqlalchemy/models/__init__.py
param_persist/sqlalchemy/models/instance_model.py
param_persist/sqlalchemy/models/param_model.py
tests/__init__.py
tests/unit_tests/__init__.py
tests/unit_tests/agents/__init__.py
tests/unit_tests/agents/test_base_agent.py
tests/unit_tests/agents/sqlalchemy_agent/__init__.py
tests/unit_tests/agents/sqlalchemy_agent/conftest.py
tests/unit_tests/agents/sqlalchemy_agent/test_sqlalchemy_agent.py
tests/unit_tests/sqlalchemy_data_models/__init__.py
tests/unit_tests/sqlalchemy_data_models/conftest.py
tests/unit_tests/sqlalchemy_data_models/test_instance_model.py
tests/unit_tests/sqlalchemy_data_models/test_param_model.py