Metadata-Version: 1.0
Name: param-persist
Version: 0.1.1
Summary: The param_persist provides functionality to persist param classes.
Home-page: https://github.com/Aquaveo/param_persist
Author: gagelarsen
Author-email: glarsen@aquaveo.com
License: BSD 2-Clause License
Platform: UNKNOWN
